vvpg_robots_go2_sdk/__init__.py
vvpg_robots_go2_sdk/py.typed
vvpg_robots_go2_sdk/unitree/__init__.py
vvpg_robots_go2_sdk/unitree/sport_streamer.py
vvpg_robots_go2_sdk-0.1.2.dist-info/METADATA
vvpg_robots_go2_sdk-0.1.2.dist-info/WHEEL
vvpg_robots_go2_sdk-0.1.2.dist-info/licenses/LICENSE
vvpg_robots_go2_sdk-0.1.2.dist-info/RECORD
