Metadata-Version: 2.4
Name: vvpg_robots_go2_sdk
Version: 0.1.2
Summary: VVPGRobots Go2 Python SDK (ROS2 Humble runtime; Unitree Sport helpers).
Project-URL: Homepage, https://github.com/<OWNER>/vvpg_robots_go2_sdk
Project-URL: Repository, https://github.com/<OWNER>/vvpg_robots_go2_sdk
Author: VVPGRobots
License: MIT
License-File: LICENSE
Keywords: go2,robotics,ros2,sdk,unitree
Classifier: Development Status :: 3 - Alpha
Classifier: License :: OSI Approved :: MIT License
Classifier: Operating System :: POSIX :: Linux
Classifier: Programming Language :: Python :: 3
Classifier: Programming Language :: Python :: 3.10
Classifier: Topic :: Software Development :: Libraries
Requires-Python: >=3.10
